dimsense/__init__.py
dimsense/feature_extraction.py
dimsense/feature_selection.py
dimsense/utils.py
dimsense-0.1.2.dist-info/LICENSE
dimsense-0.1.2.dist-info/METADATA
dimsense-0.1.2.dist-info/WHEEL
dimsense-0.1.2.dist-info/top_level.txt
dimsense-0.1.2.dist-info/RECORD
