Metadata-Version: 2.1
Name: dimsense
Version: 0.1.2
Summary: A feature selection and extraction library
Home-page: https://github.com/Tinny-Robot/DimSense
Author: Nathaniel Handan
Author-email: handanfoun@gmail.com
Classifier: Programming Language :: Python :: 3
Classifier: License :: OSI Approved :: MIT License
Classifier: Operating System :: OS Independent
Requires-Python: >=3.6
License-File: LICENSE
Requires-Dist: numpy
Requires-Dist: scikit-learn
Requires-Dist: matplotlib
Requires-Dist: pandas
Requires-Dist: tensorflow
